frontend/__init__.py
frontend/main.py
frontend/components/__init__.py
frontend/components/agent_dashboard.py
frontend/components/settings.py
Agentic_Employment-0.0.2.dist-info/LICENSE
Agentic_Employment-0.0.2.dist-info/METADATA
Agentic_Employment-0.0.2.dist-info/WHEEL
Agentic_Employment-0.0.2.dist-info/entry_points.txt
Agentic_Employment-0.0.2.dist-info/top_level.txt
Agentic_Employment-0.0.2.dist-info/RECORD
